[{"nombre":"Mijail ","apellido":"Tal","category":"ajedrez","email":"mijailElMejor@gmail.com","contrasena":"mijailElMejor","url":"/img/frase Tal.PNG"},{"nombre":"David","apellido":"Benjumea","category":"Desarrollador","email":"davidbenjumchess@gmail.com","contrasena":"123456","url":"/img/atardecer.jpg"},{"nombre":"Mati","apellido":"Rogriguez","category":"Pantalon","email":"madosamoda@gmail.com","contrasena":"$2a$10$KCnRRwsZbyNRlHJBSVSgO.KXl8.9GyC4cVa3JHne/jbQbETL76RqC","url":"/img/enanogif.gif"},{"nombre":"dasda","apellido":"dasda","category":"dajsoda","email":"matperiepno@gmail.com","contrasena":"$2a$10$F.XPs0AZSamVieMEX.4HX.YMdD8yMDKqrf/1iaXnbgztbE2aKQM52","url":"/img/carpinchonaranja.jpg"}]